streammachine/schemas/common/__init__.py
streammachine/schemas/common/common.py
streammachine_schemas_common-1.0.1.dist-info/METADATA
streammachine_schemas_common-1.0.1.dist-info/WHEEL
streammachine_schemas_common-1.0.1.dist-info/top_level.txt
streammachine_schemas_common-1.0.1.dist-info/RECORD
